<?xml version="1.0" encoding="UTF-8"?><record_update sys_domain="global" table="sysevent_email_action">
    <sysevent_email_action action="INSERT_OR_UPDATE">
        <action_insert>true</action_insert>
        <action_update>false</action_update>
        <active>true</active>
        <advanced_condition/>
        <affected_field_on_event/>
        <category display_value="Supply Chain" name="Supply Chain">70b87964db79d700a1dd7d8bbf961981</category>
        <collection>x_sthc_supply_chai_supply_chain_requests</collection>
        <condition/>
        <content_type>multipart/mixed</content_type>
        <default_interval/>
        <description/>
        <digest_from/>
        <digest_html/>
        <digest_reply_to/>
        <digest_separator_html><![CDATA[<br><hr><br>]]></digest_separator_html>
        <digest_separator_text><![CDATA[\n--------------------------------------------------------------------------------\n]]></digest_separator_text>
        <digest_subject/>
        <digest_template/>
        <digest_text/>
        <digestable>false</digestable>
        <event_name>approval.cancelled</event_name>
        <event_parm_1>false</event_parm_1>
        <event_parm_2>false</event_parm_2>
        <exclude_delegates>false</exclude_delegates>
        <force_delivery>false</force_delivery>
        <from/>
        <generation_type>engine</generation_type>
        <importance/>
        <include_attachments>true</include_attachments>
        <item>event.parm1</item>
        <item_table/>
        <mandatory>false</mandatory>
        <message/>
        <message_html><![CDATA[<p>&nbsp;</p>
<p><img style="hspace: 5px; align: left;" title="HonorHealth" src="hh_logo.pngx" alt="HonorHealth" width="100" height="50" align="left" border="0" hspace="5" vspace="0" /></p>
<p>&nbsp;</p>
<p><span style="font-family: arial, helvetica, sans-serif; font-size: 12pt;"><strong>Supply Chain&nbsp;Request&nbsp;Number: ${number} has been&nbsp;opened</strong></span></p>
<hr style="height: 2px; border: none; color: #000; background-color: #72246c;" />
<p>&nbsp;<strong><span style="font-size: 12pt;">A new Supply Chain&nbsp;Request has been opened on your behalf</span></strong></p>
<p><strong><span style="font-size: 12pt;">Request Number: </span></strong><span style="font-size: 12pt;">${number}</span></p>
<p><strong><span style="font-size: 12pt;">Description </span></strong><span style="font-size: 12pt;">${short_description}</span></p>
<p>&nbsp;</p>
<p><span style="font-size: 12pt;">Click&nbsp;<a title="here" href="supply_chain?sys_id=${sys_id}&amp;view=sp&amp;id=supply_chain_ticket&amp;table=x_sthc_supply_chai_supply_chain_requests">here</a>&nbsp;for more information on your request or to write additional comments. You can also reply to this email to&nbsp;add additional comments.</span></p>
<p><strong><span style="font-size: 12pt;">Your HonorHealth Supply Chain&nbsp;Service Desk&nbsp;<br />(480) 587 - 7277&nbsp;</span></strong></p>
<hr style="height: 2px; border: none; color: #000; background-color: #72246c;" />
<p>&nbsp;</p>
<p>&nbsp;</p>]]></message_html>
        <message_list/>
        <message_text/>
        <name>Supply Chain Request opened (Customer)</name>
        <omit_watermark>false</omit_watermark>
        <order>100</order>
        <push_message_only>false</push_message_only>
        <recipient_fields>requested_for</recipient_fields>
        <recipient_groups/>
        <recipient_users/>
        <reply_to/>
        <send_self>true</send_self>
        <sms_alternate/>
        <style/>
        <subject>Supply Chain Request Number : ${number} has been opened</subject>
        <subscribable>false</subscribable>
        <sys_class_name>sysevent_email_action</sys_class_name>
        <sys_created_by>SHollien</sys_created_by>
        <sys_created_on>2018-04-27 20:26:04</sys_created_on>
        <sys_customer_update>false</sys_customer_update>
        <sys_domain>global</sys_domain>
        <sys_id>1149fd64db79d700a1dd7d8bbf9619ed</sys_id>
        <sys_mod_count>8</sys_mod_count>
        <sys_name>Supply Chain Request opened (Customer)</sys_name>
        <sys_overrides/>
        <sys_package display_value="Supply Chain Incidents" source="x_sthc_supply_chai">ba60d82e6ff98f00277218d22e3ee42a</sys_package>
        <sys_policy/>
        <sys_replace_on_upgrade>false</sys_replace_on_upgrade>
        <sys_scope display_value="Supply Chain Incidents">ba60d82e6ff98f00277218d22e3ee42a</sys_scope>
        <sys_update_name>sysevent_email_action_1149fd64db79d700a1dd7d8bbf9619ed</sys_update_name>
        <sys_updated_by>LGOMEZ</sys_updated_by>
        <sys_updated_on>2018-08-01 17:41:30</sys_updated_on>
        <sys_version>2</sys_version>
        <template/>
        <type>email</type>
        <weight>5</weight>
    </sysevent_email_action>
</record_update>
